image_resizer/__init__.py
image_resizer/resize.py
image_resizer_lib-1.0.0.dist-info/METADATA
image_resizer_lib-1.0.0.dist-info/WHEEL
image_resizer_lib-1.0.0.dist-info/top_level.txt
image_resizer_lib-1.0.0.dist-info/RECORD
