Metadata-Version: 2.4
Name: image_resizer_lib
Version: 1.0.0
Summary: A simple Python library to resize images with CLI support.
Author: Harshith Chandra
Classifier: Programming Language :: Python :: 3
Classifier: Operating System :: OS Independent
Requires-Dist: Pillow
Dynamic: author
Dynamic: classifier
Dynamic: requires-dist
Dynamic: summary
